sqlitey/__init__.py
sqlitey-0.1.1.dist-info/METADATA
sqlitey-0.1.1.dist-info/WHEEL
sqlitey-0.1.1.dist-info/licenses/LICENSE
sqlitey-0.1.1.dist-info/RECORD
