Metadata-Version: 2.4
Name: SQLitey
Version: 0.1.1
Summary: Useful wrapper around SQLite
License: The MIT License (MIT)
License-File: LICENSE
Requires-Python: >=3.11
